saph/__init__.py
saph/saph.py
saph-1.0.dist-info/LICENSE
saph-1.0.dist-info/METADATA
saph-1.0.dist-info/WHEEL
saph-1.0.dist-info/top_level.txt
saph-1.0.dist-info/RECORD
