Metadata-Version: 2.1
Name: saph
Version: 1.0
Summary: Stupid Algorithm for Password Hashing
Home-page: https://github.com/socram8888/saph-python
Author: Marcos Del Sol Vives
Author-email: marcos@orca.pet
License: WTFPL
Project-URL: Bug Tracker, https://github.com/socram8888/saph-python/issues
Project-URL: Source Code, https://github.com/socram8888/saph-python
Keywords: password hashing hash passphrase storage
Platform: UNKNOWN
Classifier: Topic :: Security
Classifier: Topic :: Security :: Cryptography
Classifier: License :: Freely Distributable
Requires-Dist: pycryptodome (>=3.7.0)
